mcp_server_say_hello/__init__.py
mcp_server_say_hello/__main__.py
mcp_server_say_hello/server.py
mcp_server_say_hello-0.1.3.dist-info/METADATA
mcp_server_say_hello-0.1.3.dist-info/WHEEL
mcp_server_say_hello-0.1.3.dist-info/entry_points.txt
mcp_server_say_hello-0.1.3.dist-info/licenses/LICENSE
mcp_server_say_hello-0.1.3.dist-info/RECORD
